iwillgoo_server_util-0.1.9.dist-info/DESCRIPTION.rst
iwillgoo_server_util-0.1.9.dist-info/METADATA
iwillgoo_server_util-0.1.9.dist-info/RECORD
iwillgoo_server_util-0.1.9.dist-info/WHEEL
iwillgoo_server_util-0.1.9.dist-info/metadata.json
iwillgoo_server_util-0.1.9.dist-info/top_level.txt
iwillgoo_settle_util/__init__.py
iwillgoo_settle_util/oauth_client.py
iwillgoo_settle_util/oauth_server.py
