Metadata-Version: 2.0
Name: iwillgoo-server-util
Version: 0.1.9
Summary: iwillgoo bak common service
Home-page: https://github.com/packagedemo
Author: wuhanchu
Author-email: whcwuhanchu@gmail.com
License: MIT
Keywords: iwillgoo
Platform: UNKNOWN
